{"v":"5.12.1","fr":60,"ip":58,"op":240,"w":1148,"h":226,"nm":"hower","ddd":0,"assets":[{"id":"comp_0","nm":"wordmark 2","fr":24,"layers":[{"ddd":0,"ind":1,"ty":4,"nm":"k","sr":1,"ks":{"o":{"a":0,"k":100,"ix":11},"r":{"a":0,"k":0,"ix":10},"p":{"a":0,"k":[1479.373,530.5,0],"ix":2,"l":2},"a":{"a":0,"k":[-1006.372,-2272.311,0],"ix":1,"l":2},"s":{"a":0,"k":[100,100,100],"ix":6,"l":2}},"ao":0,"shapes":[{"ty":"gr","it":[{"ind":0,"ty":"sh","ix":1,"ks":{"a":0,"k":{"i":[[0,0],[0,0],[0,0],[0,0],[0,0],[0,0],[0,0],[0,0],[0,0],[0,0],[0,0],[0,0]],"o":[[0,0],[0,0],[0,0],[0,0],[0,0],[0,0],[0,0],[0,0],[0,0],[0,0],[0,0],[0,0]],"v":[[5.77,9.512],[41.7,-26.167],[15.01,-26.167],[-25.36,12.746],[-25.36,-63.091],[-46.92,-63.091],[-46.92,63.091],[-25.36,63.091],[-25.36,40.392],[-9.46,25.04],[21.94,62.974],[46.92,62.974]],"c":true},"ix":2},"nm":"Path 1","mn":"ADBE Vector Shape - Group","hd":false},{"ty":"fl","c":{"a":0,"k":[1,1,1,1],"ix":4},"o":{"a":0,"k":100,"ix":5},"r":1,"bm":0,"nm":"Fill 1","mn":"ADBE Vector Graphic - Fill","hd":false},{"ty":"tr","p":{"a":0,"k":[-1006.372,-2272.311],"ix":2},"a":{"a":0,"k":[0,0],"ix":1},"s":{"a":0,"k":[100,100],"ix":3},"r":{"a":0,"k":0,"ix":6},"o":{"a":0,"k":100,"ix":7},"sk":{"a":0,"k":0,"ix":4},"sa":{"a":0,"k":0,"ix":5},"nm":"Transform"}],"nm":"Group 7","np":2,"cix":2,"bm":0,"ix":1,"mn":"ADBE Vector Group","hd":false}],"ip":0,"op":637.5,"st":0,"ct":1,"bm":0},{"ddd":0,"ind":2,"ty":4,"nm":"c","sr":1,"ks":{"o":{"a":0,"k":100,"ix":11},"r":{"a":0,"k":0,"ix":10},"p":{"a":0,"k":[1381.121,548.976,0],"ix":2,"l":2},"a":{"a":0,"k":[-1104.624,-2253.834,0],"ix":1,"l":2},"s":{"a":0,"k":[100,100,100],"ix":6,"l":2}},"ao":0,"shapes":[{"ty":"gr","it":[{"ind":0,"ty":"sh","ix":1,"ks":{"a":0,"k":{"i":[[11.637,0],[0,16.888],[-15.741,0],[-2.9,-9.206],[0,0],[23.953,0],[-0.014,-27.836],[-28.049,0],[-3.24,20.152],[0,0]],"o":[[-15.403,0],[0,-16.889],[10.943,0],[0,0],[-3.08,-19.801],[-27.726,0],[0,27.821],[23.621,0],[0,0],[-2.91,8.868]],"v":[[1.275,27.726],[-22.578,0.081],[1.099,-27.741],[22.722,-13.237],[44.622,-13.237],[1.099,-46.342],[-44.642,-0.08],[1.451,46.342],[44.642,13.223],[22.742,13.223]],"c":true},"ix":2},"nm":"Path 1","mn":"ADBE Vector Shape - Group","hd":false},{"ty":"fl","c":{"a":0,"k":[1,1,1,1],"ix":4},"o":{"a":0,"k":100,"ix":5},"r":1,"bm":0,"nm":"Fill 1","mn":"ADBE Vector Graphic - Fill","hd":false},{"ty":"tr","p":{"a":0,"k":[-1104.624,-2253.834],"ix":2},"a":{"a":0,"k":[0,0],"ix":1},"s":{"a":0,"k":[100,100],"ix":3},"r":{"a":0,"k":0,"ix":6},"o":{"a":0,"k":100,"ix":7},"sk":{"a":0,"k":0,"ix":4},"sa":{"a":0,"k":0,"ix":5},"nm":"Transform"}],"nm":"Group 8","np":2,"cix":2,"bm":0,"ix":1,"mn":"ADBE Vector Group","hd":false}],"ip":0,"op":637.5,"st":0,"ct":1,"bm":0},{"ddd":0,"ind":3,"ty":4,"nm":"o","sr":1,"ks":{"o":{"a":0,"k":100,"ix":11},"r":{"a":0,"k":0,"ix":10},"p":{"a":0,"k":[1283.271,548.962,0],"ix":2,"l":2},"a":{"a":0,"k":[-1202.474,-2253.849,0],"ix":1,"l":2},"s":{"a":0,"k":[100,100,100],"ix":6,"l":2}},"ao":0,"shapes":[{"ty":"gr","it":[{"ind":0,"ty":"sh","ix":1,"ks":{"a":0,"k":{"i":[[16.607,0],[0,17.225],[-16.767,0],[0,-17.24]],"o":[[-16.254,0],[0,-17.226],[16.768,0],[0,17.24]],"v":[[0.176,27.741],[-25.393,0.096],[0.352,-27.901],[25.57,-0.08]],"c":true},"ix":2},"nm":"Path 1","mn":"ADBE Vector Shape - Group","hd":false},{"ind":1,"ty":"sh","ix":2,"ks":{"a":0,"k":{"i":[[28.929,0],[0,-27.66],[-28.929,0],[0,27.821]],"o":[[-28.914,0],[0,27.66],[28.929,0],[0,-27.821]],"v":[[0,-46.341],[-47.472,-0.08],[0,46.342],[47.472,-0.08]],"c":true},"ix":2},"nm":"Path 2","mn":"ADBE Vector Shape - Group","hd":false},{"ty":"fl","c":{"a":0,"k":[1,1,1,1],"ix":4},"o":{"a":0,"k":100,"ix":5},"r":1,"bm":0,"nm":"Fill 1","mn":"ADBE Vector Graphic - Fill","hd":false},{"ty":"tr","p":{"a":0,"k":[-1202.474,-2253.849],"ix":2},"a":{"a":0,"k":[0,0],"ix":1},"s":{"a":0,"k":[100,100],"ix":3},"r":{"a":0,"k":0,"ix":6},"o":{"a":0,"k":100,"ix":7},"sk":{"a":0,"k":0,"ix":4},"sa":{"a":0,"k":0,"ix":5},"nm":"Transform"}],"nm":"Group 9","np":3,"cix":2,"bm":0,"ix":1,"mn":"ADBE Vector Group","hd":false}],"ip":0,"op":637.5,"st":0,"ct":1,"bm":0},{"ddd":0,"ind":4,"ty":4,"nm":"l","sr":1,"ks":{"o":{"a":0,"k":100,"ix":11},"r":{"a":0,"k":0,"ix":10},"p":{"a":0,"k":[1218.349,530.5,0],"ix":2,"l":2},"a":{"a":0,"k":[-1267.396,-2272.311,0],"ix":1,"l":2},"s":{"a":0,"k":[100,100,100],"ix":6,"l":2}},"ao":0,"shapes":[{"ty":"gr","it":[{"ind":0,"ty":"sh","ix":1,"ks":{"a":0,"k":{"i":[[0,0],[0,0.044],[-10.856,-0.425],[0,0],[0.294,-11.094],[0,0.044],[0,0],[0,0],[0,0],[0,0]],"o":[[0,0],[0.558,10.786],[0,0],[-11.119,0.322],[0,-0.044],[0,0],[0,0],[0,0],[0,0],[0,0]],"v":[[-10.775,-22.245],[-10.775,-22.348],[9.382,-2.503],[9.572,-2.298],[-10.775,18.074],[-10.775,17.942],[-10.775,63.091],[10.775,63.091],[10.775,-63.091],[-10.775,-63.091]],"c":true},"ix":2},"nm":"Path 1","mn":"ADBE Vector Shape - Group","hd":false},{"ty":"fl","c":{"a":0,"k":[1,1,1,1],"ix":4},"o":{"a":0,"k":100,"ix":5},"r":1,"bm":0,"nm":"Fill 1","mn":"ADBE Vector Graphic - Fill","hd":false},{"ty":"tr","p":{"a":0,"k":[-1267.396,-2272.311],"ix":2},"a":{"a":0,"k":[0,0],"ix":1},"s":{"a":0,"k":[100,100],"ix":3},"r":{"a":0,"k":0,"ix":6},"o":{"a":0,"k":100,"ix":7},"sk":{"a":0,"k":0,"ix":4},"sa":{"a":0,"k":0,"ix":5},"nm":"Transform"}],"nm":"Group 10","np":2,"cix":2,"bm":0,"ix":1,"mn":"ADBE Vector Group","hd":false}],"ip":0,"op":637.5,"st":0,"ct":1,"bm":0},{"ddd":0,"ind":5,"ty":4,"nm":"b","sr":1,"ks":{"o":{"a":0,"k":100,"ix":11},"r":{"a":0,"k":0,"ix":10},"p":{"a":0,"k":[1152.833,530.514,0],"ix":2,"l":2},"a":{"a":0,"k":[-1332.912,-2272.297,0],"ix":1,"l":2},"s":{"a":0,"k":[100,100,100],"ix":6,"l":2}},"ao":0,"shapes":[{"ind":0,"ty":"sh","ix":1,"ks":{"a":0,"k":{"i":[[0,0],[0,0],[0,2.692],[0,0],[-2.64,0],[0,0],[0,-12.527],[14.362,0]],"o":[[0,0],[0,0],[0,0],[0,0],[0,0],[12.484,0],[0,10.977],[0,0]],"v":[[-1328.459,-2227.835],[-1359.926,-2227.851],[-1359.926,-2232.708],[-1359.926,-2265.082],[-1355.159,-2265.082],[-1327.77,-2265.082],[-1307.232,-2246.452],[-1328.445,-2227.821]],"c":true},"ix":2},"nm":"Path 1","mn":"ADBE Vector Shape - Group","hd":false},{"ind":1,"ty":"sh","ix":2,"ks":{"a":0,"k":{"i":[[0,0],[0,0],[0,-10.786],[14.04,0],[0,0]],"o":[[0,0],[11.457,0],[0,10.786],[0,0],[0,0]],"v":[[-1359.926,-2316.962],[-1328.958,-2316.962],[-1310.826,-2300.074],[-1331.027,-2282.146],[-1359.926,-2282.146]],"c":true},"ix":2},"nm":"Path 2","mn":"ADBE Vector Shape - Group","hd":false},{"ind":2,"ty":"sh","ix":3,"ks":{"a":0,"k":{"i":[[0,0],[0,11.664],[24.469,0],[0,0],[0,0],[0,0],[0,19.142],[13.173,4.522]],"o":[[10.269,-5.225],[0,-20.181],[0,0],[0,0],[0,0],[28.24,0],[0,-13.933],[0,0]],"v":[[-1303.828,-2274.653],[-1287.574,-2301.625],[-1326.068,-2335.388],[-1382.357,-2335.388],[-1382.357,-2209.206],[-1324.528,-2209.206],[-1283.467,-2244.534],[-1303.828,-2274.638]],"c":true},"ix":2},"nm":"Path 3","mn":"ADBE Vector Shape - Group","hd":false},{"ty":"fl","c":{"a":0,"k":[1,1,1,1],"ix":4},"o":{"a":0,"k":100,"ix":5},"r":1,"bm":0,"nm":"Fill 1","mn":"ADBE Vector Graphic - Fill","hd":false}],"ip":0,"op":637.5,"st":0,"ct":1,"bm":0},{"ddd":0,"ind":6,"ty":4,"nm":"c","sr":1,"ks":{"o":{"a":0,"k":100,"ix":11},"r":{"a":0,"k":0,"ix":10},"p":{"a":0,"k":[1049.344,547.52,0],"ix":2,"l":2},"a":{"a":0,"k":[-1436.401,-2255.291,0],"ix":1,"l":2},"s":{"a":0,"k":[100,100,100],"ix":6,"l":2}},"ao":0,"shapes":[{"ty":"gr","it":[{"ind":0,"ty":"sh","ix":1,"ks":{"a":0,"k":{"i":[[0,0],[0,0],[10.841,0],[0,16.333],[-14.802,0],[-2.67,-8.459],[0,0],[0,0],[0,0],[24.426,0],[0,-27.923],[-29.15,0],[-3.345,20.709],[0,0]],"o":[[0,0],[-2.816,8.576],[-14.89,0],[0,-16.333],[10.9,0],[0,0],[0,0],[0,0],[-3.169,-20.401],[-28.489,0],[0,27.924],[24.484,0],[0,0],[0,0]],"v":[[21.756,12.044],[21.491,12.849],[1.144,26.548],[-21.536,0.073],[0.983,-26.577],[21.506,-12.879],[21.77,-12.059],[45.902,-12.059],[45.697,-13.406],[1.012,-47.505],[-45.917,-0.088],[1.35,47.505],[45.697,13.405],[45.917,12.044]],"c":true},"ix":2},"nm":"Path 1","mn":"ADBE Vector Shape - Group","hd":false},{"ty":"fl","c":{"a":0,"k":[1,1,1,1],"ix":4},"o":{"a":0,"k":100,"ix":5},"r":1,"bm":0,"nm":"Fill 1","mn":"ADBE Vector Graphic - Fill","hd":false},{"ty":"tr","p":{"a":0,"k":[-1436.401,-2255.291],"ix":2},"a":{"a":0,"k":[0,0],"ix":1},"s":{"a":0,"k":[100,100],"ix":3},"r":{"a":0,"k":0,"ix":6},"o":{"a":0,"k":100,"ix":7},"sk":{"a":0,"k":0,"ix":4},"sa":{"a":0,"k":0,"ix":5},"nm":"Transform"}],"nm":"Group 6","np":2,"cix":2,"bm":0,"ix":1,"mn":"ADBE Vector Group","hd":false}],"ip":0,"op":637.5,"st":0,"ct":1,"bm":0},{"ddd":0,"ind":7,"ty":4,"nm":"i","sr":1,"ks":{"o":{"a":0,"k":100,"ix":11},"r":{"a":0,"k":0,"ix":10},"p":{"a":0,"k":[981.664,547.081,0],"ix":2,"l":2},"a":{"a":0,"k":[-1504.081,-2255.73,0],"ix":1,"l":2},"s":{"a":0,"k":[100,100,100],"ix":6,"l":2}},"ao":0,"shapes":[{"ty":"gr","it":[{"ind":0,"ty":"sh","ix":1,"ks":{"a":0,"k":{"i":[[0,0],[0,0],[0,0],[0,0]],"o":[[0,0],[0,0],[0,0],[0,0]],"v":[[-11.846,46.758],[11.846,46.758],[11.846,-46.758],[-11.597,-46.758]],"c":true},"ix":2},"nm":"Path 1","mn":"ADBE Vector Shape - Group","hd":false},{"ty":"fl","c":{"a":0,"k":[1,1,1,1],"ix":4},"o":{"a":0,"k":100,"ix":5},"r":1,"bm":0,"nm":"Fill 1","mn":"ADBE Vector Graphic - Fill","hd":false},{"ty":"tr","p":{"a":0,"k":[-1504.081,-2255.73],"ix":2},"a":{"a":0,"k":[0,0],"ix":1},"s":{"a":0,"k":[100,100],"ix":3},"r":{"a":0,"k":0,"ix":6},"o":{"a":0,"k":100,"ix":7},"sk":{"a":0,"k":0,"ix":4},"sa":{"a":0,"k":0,"ix":5},"nm":"Transform"}],"nm":"Group 5","np":2,"cix":2,"bm":0,"ix":1,"mn":"ADBE Vector Group","hd":false}],"ip":0,"op":637.5,"st":0,"ct":1,"bm":0},{"ddd":0,"ind":8,"ty":4,"nm":"g","sr":1,"ks":{"o":{"a":0,"k":100,"ix":11},"r":{"a":0,"k":0,"ix":10},"p":{"a":0,"k":[913.508,564.928,0],"ix":2,"l":2},"a":{"a":0,"k":[-1572.238,-2237.883,0],"ix":1,"l":2},"s":{"a":0,"k":[100,100,100],"ix":6,"l":2}},"ao":0,"shapes":[{"ty":"gr","it":[{"ind":0,"ty":"sh","ix":1,"ks":{"a":0,"k":{"i":[[14.802,0],[0,16.977],[-14.817,0],[0,-16.567]],"o":[[-15.213,0],[0,-16.976],[14.817,0],[0,16.567]],"v":[[0.799,9.301],[-24.624,-18.257],[0.799,-45.609],[25.811,-18.257]],"c":true},"ix":2},"nm":"Path 1","mn":"ADBE Vector Shape - Group","hd":false},{"ind":1,"ty":"sh","ix":2,"ks":{"a":0,"k":{"i":[[0,0],[15.212,0],[0,-25.947],[-26.025,0],[-4.211,7.595],[0,0],[18.411,0],[3.418,9],[0,0],[-25.761,0],[0,25.947],[0,0],[0,0],[0,0]],"o":[[-4.21,-7.991],[-26.817,0],[0,27.353],[14.215,0],[0,0],[0,19.772],[-11.164,0],[0,0],[2.67,19.508],[36.631,0],[0,0],[0,0],[0,0],[0,0]],"v":[[25.811,-51.405],[-3.014,-65.586],[-48.052,-18.272],[-3.014,29.043],[25.21,14.862],[25.21,16.267],[-2.413,45.42],[-25.372,30.17],[-48.228,30.17],[-1.811,65.586],[48.228,15.477],[48.228,-63.771],[25.811,-63.771],[25.811,-51.39]],"c":true},"ix":2},"nm":"Path 2","mn":"ADBE Vector Shape - Group","hd":false},{"ty":"fl","c":{"a":0,"k":[1,1,1,1],"ix":4},"o":{"a":0,"k":100,"ix":5},"r":1,"bm":0,"nm":"Fill 1","mn":"ADBE Vector Graphic - Fill","hd":false},{"ty":"tr","p":{"a":0,"k":[-1572.238,-2237.883],"ix":2},"a":{"a":0,"k":[0,0],"ix":1},"s":{"a":0,"k":[100,100],"ix":3},"r":{"a":0,"k":0,"ix":6},"o":{"a":0,"k":100,"ix":7},"sk":{"a":0,"k":0,"ix":4},"sa":{"a":0,"k":0,"ix":5},"nm":"Transform"}],"nm":"Group 1","np":3,"cix":2,"bm":0,"ix":1,"mn":"ADBE Vector Group","hd":false}],"ip":0,"op":637.5,"st":0,"ct":1,"bm":0},{"ddd":0,"ind":9,"ty":4,"nm":"a","sr":1,"ks":{"o":{"a":0,"k":100,"ix":11},"r":{"a":0,"k":0,"ix":10},"p":{"a":0,"k":[816.326,547.505,0],"ix":2,"l":2},"a":{"a":0,"k":[-1669.419,-2255.305,0],"ix":1,"l":2},"s":{"a":0,"k":[100,100,100],"ix":6,"l":2}},"ao":0,"shapes":[{"ty":"gr","it":[{"ind":0,"ty":"sh","ix":1,"ks":{"a":0,"k":{"i":[[14.656,0],[0,7.171],[-8.186,1.039],[0,0]],"o":[[-8.626,0],[0,-6.454],[0,0],[2.611,14.299]],"v":[[-4.68,28.436],[-18.059,17.313],[-5.898,6.191],[17.531,3.161]],"c":true},"ix":2},"nm":"Path 1","mn":"ADBE Vector Shape - Group","hd":false},{"ind":1,"ty":"sh","ix":2,"ks":{"a":0,"k":{"i":[[0,0],[7.247,-7.42],[-0.234,-9.015],[0,0],[0,0],[0,0],[-2.376,2.459],[-6.162,0],[0,-8.81],[0,0],[0,0],[0,-16.113],[-18.484,0],[-5.853,8.781],[-0.279,-0.029],[0,0],[0,0],[0,0],[0,0],[1.13,3.542],[20.274,0]],"o":[[-14.406,0],[-5.662,5.795],[0,0],[0,0],[0,0],[-0.146,-4.069],[2.949,-3.044],[11.325,0],[0,0],[0,0],[-19.1,2.137],[0,16.113],[13.438,0],[0.147,-0.219],[0,0],[-0.044,-0.248],[0,0],[0,0],[0,-4.303],[-4.518,-14.225],[0,0]],"v":[[1.994,-47.52],[-31.087,-36.192],[-39.39,-13.552],[-39.36,-12.41],[-17.165,-12.41],[-17.209,-13.61],[-13.834,-23.445],[0.102,-28.099],[17.912,-14.24],[17.912,-11.356],[-12.192,-8.064],[-41.809,20.24],[-11.385,47.52],[19.511,33.265],[20.186,32.943],[20.054,34.553],[19.231,45.969],[41.809,45.881],[41.809,-13.566],[40.093,-25.333],[1.981,-47.505]],"c":true},"ix":2},"nm":"Path 2","mn":"ADBE Vector Shape - Group","hd":false},{"ty":"fl","c":{"a":0,"k":[1,1,1,1],"ix":4},"o":{"a":0,"k":100,"ix":5},"r":1,"bm":0,"nm":"Fill 1","mn":"ADBE Vector Graphic - Fill","hd":false},{"ty":"tr","p":{"a":0,"k":[-1669.419,-2255.305],"ix":2},"a":{"a":0,"k":[0,0],"ix":1},"s":{"a":0,"k":[100,100],"ix":3},"r":{"a":0,"k":0,"ix":6},"o":{"a":0,"k":100,"ix":7},"sk":{"a":0,"k":0,"ix":4},"sa":{"a":0,"k":0,"ix":5},"nm":"Transform"}],"nm":"Group 3","np":3,"cix":2,"bm":0,"ix":1,"mn":"ADBE Vector Group","hd":false}],"ip":0,"op":637.5,"st":0,"ct":1,"bm":0},{"ddd":0,"ind":10,"ty":4,"nm":"m","sr":1,"ks":{"o":{"a":0,"k":100,"ix":11},"r":{"a":0,"k":0,"ix":10},"p":{"a":0,"k":[697.316,530.573,0],"ix":2,"l":2},"a":{"a":0,"k":[-1788.429,-2272.238,0],"ix":1,"l":2},"s":{"a":0,"k":[100,100,100],"ix":6,"l":2}},"ao":0,"shapes":[{"ty":"gr","it":[{"ind":0,"ty":"sh","ix":1,"ks":{"a":0,"k":{"i":[[0,0],[0,0],[0,0],[0,0],[0,0],[0,0],[0.674,21.352],[0,0],[0,0],[0,0],[0,-17.006],[0,0],[0,0],[0,0],[0,0],[0,0]],"o":[[0,0],[0,0],[0,0],[0,0],[0,0],[0,-15.982],[0,0],[0,0],[0,0],[-0.777,18.733],[0,0],[0,0],[0,0],[0,0],[0,0],[0,0]],"v":[[0.418,32.387],[-38.589,-62.974],[-68.663,-62.974],[-68.663,62.989],[-43.562,62.989],[-43.562,28.816],[-44.633,-25.304],[-8.222,61.98],[8.912,61.98],[44.912,-25.026],[43.724,28.816],[43.724,62.989],[68.663,62.989],[68.663,-62.988],[39.088,-62.988],[0.403,32.387]],"c":true},"ix":2},"nm":"Path 1","mn":"ADBE Vector Shape - Group","hd":false},{"ty":"fl","c":{"a":0,"k":[1,1,1,1],"ix":4},"o":{"a":0,"k":100,"ix":5},"r":1,"bm":0,"nm":"Fill 1","mn":"ADBE Vector Graphic - Fill","hd":false},{"ty":"tr","p":{"a":0,"k":[-1788.429,-2272.238],"ix":2},"a":{"a":0,"k":[0,0],"ix":1},"s":{"a":0,"k":[100,100],"ix":3},"r":{"a":0,"k":0,"ix":6},"o":{"a":0,"k":100,"ix":7},"sk":{"a":0,"k":0,"ix":4},"sa":{"a":0,"k":0,"ix":5},"nm":"Transform"}],"nm":"Group 4","np":2,"cix":2,"bm":0,"ix":1,"mn":"ADBE Vector Group","hd":false}],"ip":0,"op":637.5,"st":0,"ct":1,"bm":0}]},{"id":"comp_1","nm":"mask","fr":24,"layers":[{"ddd":0,"ind":1,"ty":4,"nm":"star 2","sr":1,"ks":{"o":{"a":0,"k":100,"ix":11},"r":{"a":1,"k":[{"i":{"x":[0.485],"y":[1]},"o":{"x":[0.3],"y":[0]},"t":72.5,"s":[0]},{"i":{"x":[0.248],"y":[0.64]},"o":{"x":[0.3],"y":[0]},"t":90,"s":[-3]},{"i":{"x":[0.05],"y":[1]},"o":{"x":[0.14],"y":[-0.128]},"t":112.5,"s":[13]},{"t":147.5,"s":[0],"h":1}],"ix":10},"p":{"a":1,"k":[{"i":{"x":0.485,"y":1},"o":{"x":0.3,"y":0},"t":72.5,"s":[564.901,475.414,0],"to":[0,0,0],"ti":[0,0,0]},{"i":{"x":0.248,"y":0.64},"o":{"x":0.3,"y":0},"t":90,"s":[565.151,476.414,0],"to":[0,0,0],"ti":[0,0,0]},{"i":{"x":0.05,"y":1},"o":{"x":0.14,"y":0.112},"t":112.5,"s":[570.651,469.414,0],"to":[0,0,0],"ti":[0,0,0]},{"t":147.5,"s":[564.901,475.414,0],"h":1}],"ix":2,"l":2},"a":{"a":0,"k":[0,0,0],"ix":1,"l":2},"s":{"a":0,"k":[100,100,100],"ix":6,"l":2}},"ao":0,"shapes":[{"ty":"gr","it":[{"ind":0,"ty":"sh","ix":1,"ks":{"a":0,"k":{"i":[[0,0],[2.626,13.744],[-9.908,2.244],[-0.977,-2.142],[-2.967,-14.161],[7.864,-2.94]],"o":[[0,0],[4.384,6.06],[0.97,2.452],[-2.547,0.955],[-2.706,-7.395],[-1.061,-2.229]],"v":[[-13.432,3.515],[-5.998,-16.128],[10.445,-5.345],[11.951,-1.709],[4.477,16.128],[-11.362,7.716]],"c":true},"ix":2},"nm":"Path 1","mn":"ADBE Vector Shape - Group","hd":false},{"ty":"fl","c":{"a":0,"k":[0.384313732386,0.113725490868,0.807843148708,1],"ix":4},"o":{"a":0,"k":100,"ix":5},"r":1,"bm":0,"nm":"Fill 1","mn":"ADBE Vector Graphic - Fill","hd":false},{"ty":"tr","p":{"a":0,"k":[0,0],"ix":2},"a":{"a":0,"k":[0,0],"ix":1},"s":{"a":0,"k":[100,100],"ix":3},"r":{"a":0,"k":0,"ix":6},"o":{"a":0,"k":100,"ix":7},"sk":{"a":0,"k":0,"ix":4},"sa":{"a":0,"k":0,"ix":5},"nm":"Transform"}],"nm":"Group 1","np":2,"cix":2,"bm":0,"ix":1,"mn":"ADBE Vector Group","hd":false}],"ip":15,"op":617.5,"st":-20,"ct":1,"bm":0},{"ddd":0,"ind":2,"ty":4,"nm":"hat part","sr":1,"ks":{"o":{"a":0,"k":100,"ix":11},"r":{"a":0,"k":1,"ix":10},"p":{"a":0,"k":[549.587,537.6,0],"ix":2,"l":2},"a":{"a":0,"k":[0,0,0],"ix":1,"l":2},"s":{"a":0,"k":[100,100,100],"ix":6,"l":2}},"ao":0,"shapes":[{"ty":"gr","it":[{"ind":0,"ty":"sh","ix":1,"ks":{"a":0,"k":{"i":[[0,0],[0,0]],"o":[[0,0],[0,0]],"v":[[0,-13.537],[0,13.537]],"c":false},"ix":2},"nm":"Path 1","mn":"ADBE Vector Shape - Group","hd":false},{"ty":"st","c":{"a":0,"k":[0,0,0,1],"ix":3},"o":{"a":0,"k":100,"ix":4},"w":{"a":0,"k":6.2,"ix":5},"lc":2,"lj":2,"bm":0,"nm":"Stroke 1","mn":"ADBE Vector Graphic - Stroke","hd":false},{"ty":"tr","p":{"a":0,"k":[0,0],"ix":2},"a":{"a":0,"k":[0,0],"ix":1},"s":{"a":0,"k":[100,100],"ix":3},"r":{"a":0,"k":0,"ix":6},"o":{"a":0,"k":100,"ix":7},"sk":{"a":0,"k":0,"ix":4},"sa":{"a":0,"k":0,"ix":5},"nm":"Transform"}],"nm":"Group 1","np":2,"cix":2,"bm":0,"ix":1,"mn":"ADBE Vector Group","hd":false}],"ip":0,"op":637.5,"st":0,"ct":1,"bm":0},{"ddd":0,"ind":3,"ty":4,"nm":"eyes","sr":1,"ks":{"o":{"a":0,"k":100,"ix":11},"r":{"a":1,"k":[{"i":{"x":[0.485],"y":[1]},"o":{"x":[0.3],"y":[0]},"t":72.5,"s":[0]},{"i":{"x":[0.248],"y":[0.896]},"o":{"x":[0.3],"y":[0]},"t":90,"s":[-4]},{"i":{"x":[0.05],"y":[1]},"o":{"x":[0],"y":[0]},"t":112.5,"s":[8]},{"t":145,"s":[0],"h":1}],"ix":10},"p":{"a":1,"k":[{"i":{"x":0.485,"y":1},"o":{"x":0.3,"y":0},"t":72.5,"s":[644.87,524.596,0],"to":[-0.667,-1.667,0],"ti":[-0.667,-1.667,0]},{"i":{"x":0.248,"y":0.6},"o":{"x":0.3,"y":0},"t":90,"s":[644.87,519.346,0],"to":[0,0,0],"ti":[0,0,0]},{"i":{"x":0.05,"y":1},"o":{"x":0.14,"y":0.149},"t":112.5,"s":[648.87,534.596,0],"to":[0.667,1.667,0],"ti":[-0.667,-1.667,0]},{"t":145,"s":[644.87,524.596,0],"h":1}],"ix":2,"l":2},"a":{"a":0,"k":[-1952.922,-2019.597,0],"ix":1,"l":2},"s":{"a":0,"k":[100,100,100],"ix":6,"l":2}},"ao":0,"shapes":[{"ty":"gr","it":[{"ind":0,"ty":"sh","ix":1,"ks":{"a":1,"k":[{"i":{"x":0.485,"y":1},"o":{"x":0.3,"y":0},"t":72.5,"s":[{"i":[[0,6.68],[0,0],[3.769,0],[0,-6.68],[0,0],[-3.769,0]],"o":[[0,0],[0,-8.182],[-3.769,0],[0,0],[0,8.182],[3.769,0]],"v":[[6.078,7.11],[6.078,-5.9],[-0.184,-17.673],[-6.078,-7.109],[-6.078,5.901],[0.184,17.673]],"c":true}]},{"i":{"x":0.248,"y":1},"o":{"x":0.3,"y":0},"t":90,"s":[{"i":[[0,6.68],[0,0],[3.769,0],[0,-6.68],[0,0],[-3.769,0]],"o":[[0,0],[0,-8.182],[-3.769,0],[0,0],[0,8.182],[3.769,0]],"v":[[6.078,7.11],[6.078,-5.9],[-0.184,-17.673],[-6.078,-7.109],[-6.078,5.901],[0.184,17.673]],"c":true}]},{"i":{"x":0.05,"y":1},"o":{"x":0,"y":0},"t":112.5,"s":[{"i":[[-0.114,-0.057],[0,0],[3.769,0],[-0.275,-3.42],[0,0],[-3.769,-0.039]],"o":[[0,0],[0.251,-3.76],[-3.769,0],[0,0],[0.574,2.858],[6.524,0.068]],"v":[[7.171,8.826],[7.186,8.72],[1.427,2.999],[-4.98,7.891],[-4.99,7.807],[0.897,11.521]],"c":true}]},{"t":145,"s":[{"i":[[0,6.68],[0,0],[3.769,0],[0,-6.68],[0,0],[-3.769,0]],"o":[[0,0],[0,-8.182],[-3.769,0],[0,0],[0,8.182],[3.769,0]],"v":[[6.078,7.11],[6.078,-5.9],[-0.184,-17.673],[-6.078,-7.109],[-6.078,5.901],[0.184,17.673]],"c":true}],"h":1}],"ix":2},"nm":"Path 1","mn":"ADBE Vector Shape - Group","hd":false},{"ty":"fl","c":{"a":0,"k":[0,0,0,1],"ix":4},"o":{"a":0,"k":100,"ix":5},"r":1,"bm":0,"nm":"Fill 1","mn":"ADBE Vector Graphic - Fill","hd":false},{"ty":"tr","p":{"a":0,"k":[-1939.793,-2022.866],"ix":2},"a":{"a":0,"k":[0,0],"ix":1},"s":{"a":0,"k":[100,100],"ix":3},"r":{"a":0,"k":0,"ix":6},"o":{"a":0,"k":100,"ix":7},"sk":{"a":0,"k":0,"ix":4},"sa":{"a":0,"k":0,"ix":5},"nm":"Transform"}],"nm":"R","np":2,"cix":2,"bm":0,"ix":1,"mn":"ADBE Vector Group","hd":false},{"ty":"gr","it":[{"ind":0,"ty":"sh","ix":1,"ks":{"a":1,"k":[{"i":{"x":0.485,"y":1},"o":{"x":0.3,"y":0},"t":72.5,"s":[{"i":[[0,-6.68],[0,0],[-3.769,0],[0,6.68],[0,0],[3.768,0]],"o":[[0,0],[0,8.182],[3.769,0],[0,0],[0,-8.182],[-3.769,0]],"v":[[-6.078,-7.109],[-6.078,5.901],[0.184,17.673],[6.078,7.11],[6.078,-5.9],[-0.184,-17.673]],"c":true}]},{"i":{"x":0.248,"y":1},"o":{"x":0.3,"y":0},"t":90,"s":[{"i":[[0,-6.68],[0,0],[-3.769,0],[0,6.68],[0,0],[3.768,0]],"o":[[0,0],[0,8.182],[3.769,0],[0,0],[0,-8.182],[-3.769,0]],"v":[[-6.078,-7.109],[-6.078,5.901],[0.184,17.673],[6.078,7.11],[6.078,-5.9],[-0.184,-17.673]],"c":true}]},{"i":{"x":0.05,"y":1},"o":{"x":0,"y":0},"t":112.5,"s":[{"i":[[0,-6.68],[0,0],[-3.769,0],[0,6.68],[0,0],[3.768,0]],"o":[[0,0],[0,8.182],[3.769,0],[0,0],[0,-8.182],[-3.769,0]],"v":[[-6.121,-3.821],[-6.105,2.118],[0.157,13.89],[6.051,3.327],[6.035,-2.612],[-0.227,-14.385]],"c":true}]},{"t":145,"s":[{"i":[[0,-6.68],[0,0],[-3.769,0],[0,6.68],[0,0],[3.768,0]],"o":[[0,0],[0,8.182],[3.769,0],[0,0],[0,-8.182],[-3.769,0]],"v":[[-6.078,-7.109],[-6.078,5.901],[0.184,17.673],[6.078,7.11],[6.078,-5.9],[-0.184,-17.673]],"c":true}],"h":1}],"ix":2},"nm":"Path 1","mn":"ADBE Vector Shape - Group","hd":false},{"ty":"fl","c":{"a":0,"k":[0,0,0,1],"ix":4},"o":{"a":0,"k":100,"ix":5},"r":1,"bm":0,"nm":"Fill 1","mn":"ADBE Vector Graphic - Fill","hd":false},{"ty":"tr","p":{"a":0,"k":[-1966.051,-2016.328],"ix":2},"a":{"a":0,"k":[0,0],"ix":1},"s":{"a":0,"k":[100,100],"ix":3},"r":{"a":0,"k":0,"ix":6},"o":{"a":0,"k":100,"ix":7},"sk":{"a":0,"k":0,"ix":4},"sa":{"a":0,"k":0,"ix":5},"nm":"Transform"}],"nm":"L","np":2,"cix":2,"bm":0,"ix":2,"mn":"ADBE Vector Group","hd":false}],"ip":0,"op":637.5,"st":0,"ct":1,"bm":0}]}],"layers":[{"ddd":0,"ind":1,"ty":4,"nm":"star 2","parent":2,"sr":1,"ks":{"o":{"a":0,"k":100,"ix":11},"r":{"a":0,"k":0,"ix":10},"p":{"a":1,"k":[{"i":{"x":0.05,"y":1},"o":{"x":0.627,"y":0},"t":72.5,"s":[982.053,479.855,0],"to":[0,0,0],"ti":[0,0,0]},{"i":{"x":0.572,"y":0.837},"o":{"x":0.364,"y":0},"t":117.5,"s":[982.053,489.855,0],"to":[0,0,0],"ti":[0,0,0]},{"i":{"x":0.373,"y":1},"o":{"x":0.151,"y":0.179},"t":135,"s":[982.053,461.855,0],"to":[0,0,0],"ti":[0,0,0]},{"t":170,"s":[982.053,479.855,0]}],"ix":2,"l":2},"a":{"a":0,"k":[-1503.692,-2322.955,0],"ix":1,"l":2},"s":{"a":1,"k":[{"i":{"x":[0.05,0.05,0.05],"y":[1,1,1]},"o":{"x":[0.627,0.627,0.95],"y":[0,0,0]},"t":72.5,"s":[100,100,100]},{"i":{"x":[0.572,0.572,0.572],"y":[0.824,0.824,0.837]},"o":{"x":[0.364,0.364,0.364],"y":[0,0,0]},"t":117.5,"s":[101,101,100]},{"i":{"x":[0.373,0.373,0.05],"y":[1,1,1]},"o":{"x":[0.151,0.151,0.151],"y":[-0.122,-0.122,0.115]},"t":135,"s":[152,152,100]},{"t":170,"s":[100,100,100]}],"ix":6,"l":2}},"ao":0,"ef":[{"ty":5,"nm":"Elastic Controller","np":5,"mn":"Pseudo/MDS Elastic Controller","ix":1,"en":1,"ef":[{"ty":0,"nm":"Amplitude","mn":"Pseudo/MDS Elastic Controller-0001","ix":1,"v":{"a":0,"k":9,"ix":1}},{"ty":0,"nm":"Frequency","mn":"Pseudo/MDS Elastic Controller-0002","ix":2,"v":{"a":0,"k":58,"ix":2}},{"ty":0,"nm":"Decay","mn":"Pseudo/MDS Elastic Controller-0003","ix":3,"v":{"a":0,"k":47,"ix":3}}]}],"shapes":[{"ty":"gr","it":[{"ind":0,"ty":"sh","ix":1,"ks":{"a":0,"k":{"i":[[0.484,9.235],[9.301,-0.351],[0,0],[-0.264,-9.498],[-9.521,0.278],[0,0]],"o":[[-0.484,9.249],[0,0],[9.521,0.278],[0.249,-9.513],[0,0],[-9.3,-0.351]],"v":[[0,-17.306],[-17.267,-0.315],[-17.428,-0.139],[0,17.306],[17.428,-0.139],[17.266,-0.315]],"c":true},"ix":2},"nm":"Path 1","mn":"ADBE Vector Shape - Group","hd":false},{"ty":"fl","c":{"a":0,"k":[1,1,1,1],"ix":4},"o":{"a":0,"k":100,"ix":5},"r":1,"bm":0,"nm":"Fill 1","mn":"ADBE Vector Graphic - Fill","hd":false},{"ty":"tr","p":{"a":0,"k":[-1503.692,-2322.955],"ix":2},"a":{"a":0,"k":[0,0],"ix":1},"s":{"a":0,"k":[100,100],"ix":3},"r":{"a":0,"k":0,"ix":6},"o":{"a":0,"k":100,"ix":7},"sk":{"a":0,"k":0,"ix":4},"sa":{"a":0,"k":0,"ix":5},"nm":"Transform"}],"nm":"Group 2","np":2,"cix":2,"bm":0,"ix":1,"mn":"ADBE Vector Group","hd":false}],"ip":17.5,"op":532.5,"st":-105,"ct":1,"bm":0},{"ddd":0,"ind":2,"ty":0,"nm":"wordmark 2","refId":"comp_0","sr":1,"ks":{"o":{"a":0,"k":100,"ix":11},"r":{"a":0,"k":0,"ix":10},"p":{"a":0,"k":[577,133.5,0],"ix":2,"l":2},"a":{"a":0,"k":[960,540,0],"ix":1,"l":2},"s":{"a":0,"k":[100,100,100],"ix":6,"l":2}},"ao":0,"w":1920,"h":1080,"ip":0,"op":637.5,"st":0,"ct":1,"bm":0},{"ddd":0,"ind":3,"ty":0,"nm":"mask","parent":5,"td":1,"refId":"comp_1","sr":1,"ks":{"o":{"a":0,"k":100,"ix":11},"r":{"a":0,"k":0,"ix":10},"p":{"a":0,"k":[341.765,10.148,0],"ix":2,"l":2},"a":{"a":0,"k":[960,540,0],"ix":1,"l":2},"s":{"a":0,"k":[100,100,100],"ix":6,"l":2}},"ao":0,"w":1920,"h":1080,"ip":0,"op":637.5,"st":0,"ct":1,"bm":0},{"ddd":0,"ind":4,"ty":4,"nm":"hat","parent":5,"tt":2,"tp":3,"sr":1,"ks":{"o":{"a":0,"k":100,"ix":11},"r":{"a":1,"k":[{"i":{"x":[0.485],"y":[1]},"o":{"x":[0.3],"y":[0]},"t":72.5,"s":[0]},{"i":{"x":[0.248],"y":[0.868]},"o":{"x":[0.3],"y":[0]},"t":90,"s":[-2.8]},{"i":{"x":[0.05],"y":[1]},"o":{"x":[0],"y":[0]},"t":112.5,"s":[15]},{"t":145,"s":[0],"h":1}],"ix":10},"p":{"a":1,"k":[{"i":{"x":0.485,"y":1},"o":{"x":0.3,"y":0},"t":72.5,"s":[-10.116,-32.367,0],"to":[0,-0.542,0],"ti":[0,0,0]},{"i":{"x":0.248,"y":0.94},"o":{"x":0.3,"y":0},"t":90,"s":[-10.116,-32.367,0],"to":[0,0.542,0],"ti":[0,0,0]},{"i":{"x":0.054,"y":1},"o":{"x":0,"y":0},"t":112.5,"s":[-10.116,-29.117,0],"to":[0,0,0],"ti":[0,0.208,0]},{"t":145,"s":[-10.116,-32.367,0],"h":1}],"ix":2,"l":2},"a":{"a":0,"k":[10,52.25,0],"ix":1,"l":2},"s":{"a":0,"k":[100,100,100],"ix":6,"l":2}},"ao":0,"shapes":[{"ty":"gr","it":[{"ind":0,"ty":"sh","ix":1,"ks":{"a":0,"k":{"i":[[-2.616,1.03],[-11.07,3.014],[-12.411,1.72],[0,0],[-0.019,-6.293],[0,0]],"o":[[10.003,-3.921],[13.129,-3.581],[0,0],[-5.771,-2.504],[0,0],[6.291,-4.044]],"v":[[-23.08,22.592],[8.647,12.123],[47.194,4.149],[-35,-32.463],[-47.194,-24.432],[-47.042,33.193]],"c":true},"ix":2},"nm":"Path 1","mn":"ADBE Vector Shape - Group","hd":false},{"ty":"fl","c":{"a":0,"k":[1,1,1,1],"ix":4},"o":{"a":0,"k":100,"ix":5},"r":1,"bm":0,"nm":"Fill 1","mn":"ADBE Vector Graphic - Fill","hd":false},{"ty":"tr","p":{"a":0,"k":[0,0],"ix":2},"a":{"a":0,"k":[0,0],"ix":1},"s":{"a":0,"k":[100,100],"ix":3},"r":{"a":0,"k":0,"ix":6},"o":{"a":0,"k":100,"ix":7},"sk":{"a":0,"k":0,"ix":4},"sa":{"a":0,"k":0,"ix":5},"nm":"Transform"}],"nm":"Group 1","np":2,"cix":2,"bm":0,"ix":1,"mn":"ADBE Vector Group","hd":false}],"ip":0,"op":615,"st":0,"ct":1,"bm":0},{"ddd":0,"ind":5,"ty":4,"nm":"body","tt":2,"tp":3,"sr":1,"ks":{"o":{"a":0,"k":100,"ix":11},"r":{"a":0,"k":0,"ix":10},"p":{"a":0,"k":[109.253,213.68,0],"ix":2,"l":2},"a":{"a":0,"k":[-1.983,76.328,0],"ix":1,"l":2},"s":{"a":1,"k":[{"i":{"x":[0.485,0.485,0.485],"y":[1,1,1]},"o":{"x":[0.3,0.3,0.3],"y":[0,0,0]},"t":72.5,"s":[100,100,100]},{"i":{"x":[0.248,0.248,0.248],"y":[1,1,1]},"o":{"x":[0.3,0.3,0.3],"y":[0,0,0]},"t":90,"s":[100,110,100]},{"i":{"x":[0.05,0.05,0.05],"y":[1,1,1]},"o":{"x":[0.001,0.001,0.001],"y":[0,0,0]},"t":112.5,"s":[105,97,100]},{"t":145,"s":[100,100,100],"h":1}],"ix":6,"l":2}},"ao":0,"shapes":[{"ty":"gr","it":[{"ind":0,"ty":"sh","ix":1,"ks":{"a":1,"k":[{"i":{"x":0.485,"y":1},"o":{"x":0.3,"y":0},"t":72.5,"s":[{"i":[[5.029,10.459],[31.876,-13.261],[-84.705,-6.704],[-9.865,-4.231],[-7.782,5.512],[-0.34,88.917]],"o":[[-15.845,-32.952],[-38.278,13.464],[1.486,7.864],[7.167,2.366],[82.074,-38.466],[26.866,-13.933]],"v":[[105.36,-59.65],[-42.114,-55.033],[-65.379,13.645],[-59.684,49.494],[-5.826,75.639],[65.383,-17.891]],"c":true}]},{"i":{"x":0.248,"y":1},"o":{"x":0.3,"y":0},"t":90,"s":[{"i":[[5.157,10.397],[31.876,-13.261],[-84.504,5.333],[-9.865,-4.231],[-7.782,5.512],[-0.34,88.917]],"o":[[-14.877,-29.992],[-38.278,13.464],[1.486,7.864],[7.167,2.366],[82.074,-38.466],[25.8,-21.295]],"v":[[100.455,-66.657],[-42.114,-52.931],[-65.379,16.448],[-59.684,49.494],[-5.826,75.639],[65.383,-17.891]],"c":true}]},{"i":{"x":0.05,"y":1},"o":{"x":0,"y":0},"t":112.5,"s":[{"i":[[0.947,10.305],[60.513,-6.845],[-78.197,-31.819],[-9.865,-4.231],[-7.782,5.512],[-8.585,68.372]],"o":[[-4.392,-36.313],[-37.894,7.402],[1.486,7.864],[7.167,2.366],[82.074,-38.466],[35.786,-3.86]],"v":[[115.818,-26.907],[-42.612,-58.501],[-65.379,3.145],[-59.684,49.494],[-5.826,75.639],[70.114,-5.192]],"c":true}]},{"t":145,"s":[{"i":[[5.029,10.459],[31.876,-13.261],[-84.705,-6.704],[-9.865,-4.231],[-7.782,5.512],[-0.34,88.917]],"o":[[-15.845,-32.952],[-38.278,13.464],[1.486,7.864],[7.167,2.366],[82.074,-38.466],[26.866,-13.933]],"v":[[105.36,-59.65],[-42.114,-55.033],[-65.379,13.645],[-59.684,49.494],[-5.826,75.639],[65.383,-17.891]],"c":true}],"h":1}],"ix":2},"nm":"Path 1","mn":"ADBE Vector Shape - Group","hd":false},{"ty":"fl","c":{"a":0,"k":[1,1,1,1],"ix":4},"o":{"a":0,"k":100,"ix":5},"r":1,"bm":0,"nm":"Fill 1","mn":"ADBE Vector Graphic - Fill","hd":false},{"ty":"tr","p":{"a":0,"k":[0,0],"ix":2},"a":{"a":0,"k":[0,0],"ix":1},"s":{"a":0,"k":[100,100],"ix":3},"r":{"a":0,"k":0,"ix":6},"o":{"a":0,"k":100,"ix":7},"sk":{"a":0,"k":0,"ix":4},"sa":{"a":0,"k":0,"ix":5},"nm":"Transform"}],"nm":"Group 1","np":2,"cix":2,"bm":0,"ix":1,"mn":"ADBE Vector Group","hd":false}],"ip":0,"op":615,"st":0,"ct":1,"bm":0}],"markers":[],"props":{}}